{
	"metadata": {
		"name": "crown",
		"spoiler": false,
		"beta": false
	},
	"content": {
		"color": 12846604,
		"description": "Character gains 7% more experience.",
		"fields": [
			{
				"inline": false,
				"name": "Unlocks",
				"value": "Unlocked by: Reaching Level 10 with any character."
			},
			{
				"inline": false,
				"name": "Evolution",
				"value": "Required to evolve **Pentagram** to **Gorgeous Moon**"
			}
		],
		"footer": {
			"icon_url": "https://ucarecdn.com/dc6980a3-c7d4-4164-9b02-276ea7832791/BotIcon.png",
			"text": "Vampire Bot @ github.com/SHA65536/Vampire-Survivors-Bot"
		},
		"thumbnail": {
			"url": "https://ucarecdn.com/849c3e36-4011-4d11-9579-a22f42f8a078/Crown.png"
		},
		"title": "Crown"
	}
}